galaxy/__init__.py
galaxy/py.typed
galaxy/selenium/__init__.py
galaxy/selenium/axe_results.py
galaxy/selenium/cli.py
galaxy/selenium/context.py
galaxy/selenium/driver_factory.py
galaxy/selenium/has_driver.py
galaxy/selenium/jupyter_context.py
galaxy/selenium/navigates_galaxy.py
galaxy/selenium/sizzle.py
galaxy/selenium/smart_components.py
galaxy/selenium/scripts/__init__.py
galaxy/selenium/scripts/dump_tour.py
galaxy/selenium/toolbox/__init__.py
galaxy/selenium/toolbox/filters.py
galaxy_selenium-25.0.3.dist-info/licenses/LICENSE
galaxy_selenium-25.0.3.dist-info/METADATA
galaxy_selenium-25.0.3.dist-info/WHEEL
galaxy_selenium-25.0.3.dist-info/entry_points.txt
galaxy_selenium-25.0.3.dist-info/top_level.txt
galaxy_selenium-25.0.3.dist-info/RECORD
